{
  "id": "trincado",
  "name": "Trincado",
  "type": "habilidade_de_classe",
  "sub_type": "poder_de_lutador",
  "description": "Esculpido à exaustão, seu corpo se tornou uma máquina. Você soma seu modificador de Constituição nas suas rolagens de dano desarmado.",
  "requirements": [
     {
      "type": "character_lvl",
      "sub_type": "hard",
      "value": 10
    },
    {
      "type": "attr_value",
      "sub_type": "hard",
      "attr": "con",
      "value": 17
    },
    {
      "type": "feature",
      "sub_type": "hard",
      "id": "sarado"
    },
    {
      "type": "attack_type",
      "sub_type": "soft",
      "attack": "desarmado"
    }
  ],
  "effects": [
    {
      "type": "add_damage_attr",
      "attr": "con"
    }
  ],
  "costs": null
}
